
{
  "registry_name": "byg:cryptic_redstone",
  "worldgen/configured_feature": {
    "config": {
      "targets": [
        {
          "target": {
            "block": "byg:cryptic_stone",
            "predicate_type": "minecraft:block_match"
          },
          "state": {
            "Properties": {
              "lit": "false"
            },
            "Name": "byg:cryptic_redstone_ore"
          }
        }
      ],
      "size": 8,
      "discard_chance_on_air_exposure": 0.0
    },
    "type": "minecraft:ore"
  }
}